urld/__init__.py
urld/__main__.py
urld/version.py
urld-0.1.2.dist-info/LICENSE
urld-0.1.2.dist-info/METADATA
urld-0.1.2.dist-info/WHEEL
urld-0.1.2.dist-info/entry_points.txt
urld-0.1.2.dist-info/top_level.txt
urld-0.1.2.dist-info/RECORD
