Metadata-Version: 2.1
Name: urld
Version: 0.1.2
Summary: Descompose URL in parts.
Home-page: https://gitlab.com/Zer1t0/urld
Author: Eloy Perez
Author-email: zer1t0ps@protonmail.com
Classifier: Programming Language :: Python :: 3
Classifier: License :: OSI Approved :: GNU General Public License v3 (GPLv3)
License-File: LICENSE
